modlib/__init__.py
sqiul83-1.0.dist-info/licenses/LICENSE.TXT
sqiul83-1.0.dist-info/METADATA
sqiul83-1.0.dist-info/WHEEL
sqiul83-1.0.dist-info/top_level.txt
sqiul83-1.0.dist-info/RECORD
